cabifyStopPrice.py
cabifyStopPrice-0.1.0.dist-info/LICENSE.md
cabifyStopPrice-0.1.0.dist-info/METADATA
cabifyStopPrice-0.1.0.dist-info/WHEEL
cabifyStopPrice-0.1.0.dist-info/top_level.txt
cabifyStopPrice-0.1.0.dist-info/RECORD
