Metadata-Version: 2.1
Name: cabifyStopPrice
Version: 0.1.0
Summary: Calculates the price of a stop in a Cabify trip
Author: Ignacio Fernandez
Classifier: Programming Language :: Python :: 3
Classifier: License :: OSI Approved :: MIT License
Classifier: Operating System :: OS Independent
Requires-Python: >=3.6
License-File: LICENSE.md
